COPYING
README.md
pyproject.toml
setup.cfg
setup.py
src/minifit/__init__.py
src/minifit/exponential.py
src/minifit/fit_base.py
src/minifit/gauss.py
src/minifit/lennard_jones.py
src/minifit/morse.py
src/minifit/poly.py
src/minifit/user_defined.py
src/minifit.egg-info/PKG-INFO
src/minifit.egg-info/SOURCES.txt
src/minifit.egg-info/dependency_links.txt
src/minifit.egg-info/requires.txt
src/minifit.egg-info/top_level.txt
src/minifit/tests/__init__.py
src/minifit/tests/common.py
src/minifit/tests/test_exponential.py
src/minifit/tests/test_gauss.py
src/minifit/tests/test_lennard_jones.py
src/minifit/tests/test_morse.py
src/minifit/tests/test_poly.py
src/minifit/tests/test_user.py