Metadata-Version: 2.1
Name: minifit
Version: 1.0.5
Summary: MiniFit is a python package that can be used for fitting data.
Home-page: https://gitlab.com/mike3.14/minifit
Author: Michał Kopczyński
Author-email: michal.kopczynski3.14@gmail.com
License: GPL-3.0
Project-URL: repository, https://gitlab.com/mike3.14/minifit
Platform: UNKNOWN
Classifier: Environment :: Console
Classifier: Intended Audience :: Science/Research
Classifier: License :: OSI Approved :: GNU General Public License (GPL)
Classifier: Operating System :: MacOS
Classifier: Operating System :: POSIX :: Linux
Classifier: Programming Language :: Python :: 3
Classifier: Topic :: Scientific/Engineering :: Physics
Classifier: Topic :: Scientific/Engineering :: Chemistry
Requires-Python: >=3.8
License-File: COPYING
